colorizelatextables/__init__.py
colorizelatextables/colorize_table.py
colorizelatextables-1.1.data/scripts/colorize_table.py
colorizelatextables-1.1.dist-info/LICENSE
colorizelatextables-1.1.dist-info/METADATA
colorizelatextables-1.1.dist-info/WHEEL
colorizelatextables-1.1.dist-info/top_level.txt
colorizelatextables-1.1.dist-info/RECORD
