Metadata-Version: 2.1
Name: colorizelatextables
Version: 1.1
Summary: Utility script to transform csv files or pandas dataframes to colorized LaTex tables
Home-page: https://github.com/dobraczka/ColorizeLaTexTables
Author: Daniel Obraczka
Author-email: 
License: UNKNOWN
Platform: UNKNOWN
Classifier: Topic :: Text Processing :: Markup :: LaTeX
Classifier: License :: OSI Approved :: MIT License
Classifier: Topic :: Scientific/Engineering :: Visualization
